flatdata/generator/__init__.py
flatdata/generator/app.py
flatdata/generator/engine.py
flatdata/generator/grammar.py
flatdata/generator/generators/__init__.py
flatdata/generator/generators/cpp.py
flatdata/generator/generators/dot.py
flatdata/generator/generators/flatdata.py
flatdata/generator/generators/go.py
flatdata/generator/generators/python.py
flatdata/generator/generators/rust.py
flatdata/generator/templates/__init__.py
flatdata/generator/templates/cpp/__init__.py
flatdata/generator/templates/cpp/archive.jinja2
flatdata/generator/templates/cpp/constant.jinja2
flatdata/generator/templates/cpp/cpp.jinja2
flatdata/generator/templates/cpp/enumeration.jinja2
flatdata/generator/templates/cpp/namespace.jinja2
flatdata/generator/templates/cpp/resource.jinja2
flatdata/generator/templates/cpp/structure.jinja2
flatdata/generator/templates/dot/__init__.py
flatdata/generator/templates/dot/archive.jinja2
flatdata/generator/templates/dot/dot.jinja2
flatdata/generator/templates/dot/namespace.jinja2
flatdata/generator/templates/dot/references.jinja2
flatdata/generator/templates/dot/render.jinja2
flatdata/generator/templates/dot/resource.jinja2
flatdata/generator/templates/dot/structure.jinja2
flatdata/generator/templates/dot/styles.jinja2
flatdata/generator/templates/flatdata/__init__.py
flatdata/generator/templates/flatdata/archive.jinja2
flatdata/generator/templates/flatdata/constant.jinja2
flatdata/generator/templates/flatdata/enumeration.jinja2
flatdata/generator/templates/flatdata/flatdata.jinja2
flatdata/generator/templates/flatdata/namespace.jinja2
flatdata/generator/templates/flatdata/resource.jinja2
flatdata/generator/templates/flatdata/structure.jinja2
flatdata/generator/templates/go/__init__.py
flatdata/generator/templates/go/archive.jinja2
flatdata/generator/templates/go/base.jinja2
flatdata/generator/templates/go/go.jinja2
flatdata/generator/templates/go/instance.jinja2
flatdata/generator/templates/go/multivector.jinja2
flatdata_generator-0.4.6.dist-info/METADATA
flatdata_generator-0.4.6.dist-info/WHEEL
flatdata_generator-0.4.6.dist-info/entry_points.txt
flatdata_generator-0.4.6.dist-info/RECORD
