Metadata-Version: 2.3
Name: flatdata-generator
Version: 0.4.6
Summary: Generate source code for C++, Rust, Go or Python from a Flatdata schema file
Project-URL: Homepage, https://github.com/heremaps/flatdata
Author: Flatdata Developers
Classifier: License :: OSI Approved :: Apache Software License
Classifier: Operating System :: OS Independent
Classifier: Programming Language :: Python :: 3
Requires-Dist: jinja2>=2.2
Requires-Dist: pyparsing>=2.0
